leoprofanity/LeoProfanity.py
leoprofanity/__init__.py
leoprofanity/__main__.py
leoprofanity/dictionary/default.json
leoprofanity-0.0.4.dist-info/LICENSE
leoprofanity-0.0.4.dist-info/METADATA
leoprofanity-0.0.4.dist-info/WHEEL
leoprofanity-0.0.4.dist-info/entry_points.txt
leoprofanity-0.0.4.dist-info/top_level.txt
leoprofanity-0.0.4.dist-info/RECORD
