Metadata-Version: 2.1
Name: leoprofanity
Version: 0.0.4
Summary: Profanity filter, based on Shutterstock dictionary
Home-page: https://github.com/jojoee/leo-profanity-python
Author: Nathachai Thongniran
Author-email: inid3a@gmail.com
License: MIT
Platform: UNKNOWN
Classifier: License :: OSI Approved :: MIT License
Classifier: Programming Language :: Python :: 3
Classifier: Programming Language :: Python :: 3.7
Provides-Extra: dev
Requires-Dist: black ; extra == 'dev'
Requires-Dist: flake8 ; extra == 'dev'
Requires-Dist: pytype ; extra == 'dev'
